pbd/__init__.py
pbd/base.py
pbd/bookmarks.py
pbd/followings.py
pbd/main.py
pbd/pixiv_types.py
pbd/py.typed
pixiv_bulk_downloader-2.8.1.dist-info/LICENSE
pixiv_bulk_downloader-2.8.1.dist-info/METADATA
pixiv_bulk_downloader-2.8.1.dist-info/WHEEL
pixiv_bulk_downloader-2.8.1.dist-info/entry_points.txt
pixiv_bulk_downloader-2.8.1.dist-info/top_level.txt
pixiv_bulk_downloader-2.8.1.dist-info/RECORD
