Metadata-Version: 2.1
Name: pixiv-bulk-downloader
Version: 2.8.1
Summary: Pixiv Bulk Downloader for bookmarks and works of followed authors
Home-page: https://github.com/eggplants/pixiv-bulk-downloader
Author: eggplants
Author-email: w10776e8w@yahoo.co.jp
License: MIT
Classifier: License :: OSI Approved :: MIT License
Classifier: Programming Language :: Python
Classifier: Programming Language :: Python :: 3
Classifier: Programming Language :: Python :: 3 :: Only
Classifier: Programming Language :: Python :: Implementation :: CPython
Requires-Python: >=3.7
License-File: LICENSE
Requires-Dist: PixivPy3 (==3.7.1)
Requires-Dist: gppt (==2.2.0)
Requires-Dist: pwinput (==1.0.2)
Provides-Extra: dev
Requires-Dist: black ; extra == 'dev'
Requires-Dist: flake8 ; extra == 'dev'
Requires-Dist: mypy ; extra == 'dev'
Requires-Dist: setuptools (>=46.4.0) ; extra == 'dev'
Requires-Dist: types-setuptools ; extra == 'dev'
